<?xml version="1.0" encoding="utf-8" ?>
<dwsync>
<file name="index.php" server="C:/wamp/www/genesis/" local="130867343844151343" remote="130867343840000000" />
<file name="xxxxindex.php" server="C:/wamp/www/genesis/" local="130844688998371792" remote="130844688990000000" />
<file name="xxxxindex - Copy.php" server="C:/wamp/www/genesis/" local="130851729800203197" remote="130851729800000000" />
<file name="indexHidden.php" server="C:/wamp/www/genesis/" local="130849324710000000" remote="130849324710000000" />
<file name="indexFiltroHidden.php" server="C:/wamp/www/genesis/" local="130863066103206768" remote="130863066100000000" />
<file name="pessoasInc.inc" server="C:/wamp/www/genesis/" local="130851289497099635" remote="130851289490000000" />
<file name="xxindex2.php" server="C:/wamp/www/genesis/" local="130855914150000000" remote="130855914150000000" />
<file name="pessoas.php" server="C:/wamp/www/genesis/" local="130867344546285710" remote="130867344540000000" />
</dwsync>